{
  "id": 1350,
  "guid": "2a4d05da-97fd-4e1b-ad80-48a18c8c1d9b",
  "url": "https://events.ccc.de/camp/2019/wiki/Session:Aktuelle_Digimodes",
  "logo": null,
  "date": "2019-08-24T19:00:00+02:00",
  "start": "19:00",
  "duration": "1:00",
  "room": "Village:Chaoswelle",
  "slug": "camp2019-1350-session_aktuelle_digimodes",
  "title": "Aktuelle Digimodes",
  "subtitle": "",
  "track": "self organized sessions",
  "type": "talk",
  "language": "de",
  "abstract": "",
  "description": "Ein Blick in die Trickkiste der modernen Digimodes JT65/JT9 und FT8/FT4.",
  "persons": [
    {
      "id": 0,
      "url": "https://events.ccc.de/camp/2019/wiki/User:Pylon",
      "public_name": "Pylon"
    }
  ],
  "links": []
}