{
  "id": 1480,
  "guid": "d0b6d3d7-a2e9-4d6a-84f1-f5fb08172cfa",
  "url": "https://events.ccc.de/camp/2019/wiki/Session:Poly*-/RA-Meetup",
  "logo": null,
  "date": "2019-08-23T16:00:00+02:00",
  "start": "16:00",
  "duration": "2:00",
  "room": "Johnson (Workshop 1)",
  "slug": "camp2019-1480-session_poly_ra_meetup",
  "title": "Poly*-/RA-Meetup",
  "subtitle": "",
  "track": "self organized sessions",
  "type": "meeting",
  "language": "de",
  "abstract": "",
  "description": "Let's hang around, talk about concepts of interpersonal relationships",
  "persons": [
    {
      "id": 0,
      "url": "https://events.ccc.de/camp/2019/wiki/User:Binbash",
      "public_name": "Binbash"
    },
    {
      "id": 0,
      "url": "https://events.ccc.de/camp/2019/wiki/User:Poly",
      "public_name": "Poly"
    }
  ],
  "links": []
}